petri/__init__.py
petri/dot_env.py
petri/ext.py
petri/loggin.py
petri/metadata.py
petri/settings.py
petri-0.24.1.dist-info/WHEEL
petri-0.24.1.dist-info/METADATA
petri-0.24.1.dist-info/RECORD
