Metadata-Version: 2.1
Name: petri
Version: 0.24.1
Summary: Free your python code from 12-factor boilerplate.
Home-page: https://pypi.org/project/petri/
License: Unlicense
Keywords: dotenv,boilerplate,12-factor,pydantic,structlog
Author: Pablo Woolvett
Author-email: pablowoolvett@gmail.com
Requires-Python: >=3.6,<4.0
Classifier: License :: Other/Proprietary License
Classifier: Programming Language :: Python :: 3
Classifier: Programming Language :: Python :: 3.6
Classifier: Programming Language :: Python :: 3.7
Provides-Extra: color
Provides-Extra: docs
Provides-Extra: lint
Provides-Extra: pytest
Requires-Dist: colorama (>=0.4.1,<0.5.0); extra == "color"
Requires-Dist: importlib_metadata (>=0.23,<0.24)
Requires-Dist: pydantic (>=0.32.2,<0.33.0)
Requires-Dist: python-dotenv (>=0.10.3,<0.11.0)
Requires-Dist: structlog (>=19.1.0,<20.0.0)
Project-URL: Documentation, https://petri.readthedocs.io/en/stable/
Project-URL: Repository, https://github.com/pwoolvett/petri
